Metadata-Version: 2.1
Name: nexus-upload
Version: 0.0.3
Summary: Upload packages to Nexus server
Home-page: https://github.com/gebing/nexus_upload
Author: gebing
Author-email: gebing@foxmail.com
License: Apache License 2.0
Keywords: nexus package upload
Platform: any
Classifier: Development Status :: 3 - Alpha
Classifier: License :: OSI Approved :: Apache Software License
Classifier: Programming Language :: Python :: 2.7
Classifier: Programming Language :: Python :: 3.5
Classifier: Programming Language :: Python :: 3.6
Classifier: Programming Language :: Python :: 3.7
Classifier: Topic :: System :: Distributed Computing
Classifier: Topic :: System :: Networking
